opsys_relay_controller/__init__.py
opsys_relay_controller/relay_abstract.py
opsys_relay_controller/relay_controller.py
opsys_relay_controller/relay_types.py
opsys_relay_controller-0.0.3.dist-info/LICENSE
opsys_relay_controller-0.0.3.dist-info/METADATA
opsys_relay_controller-0.0.3.dist-info/WHEEL
opsys_relay_controller-0.0.3.dist-info/top_level.txt
opsys_relay_controller-0.0.3.dist-info/RECORD
