Metadata-Version: 2.1
Name: opsys-relay-controller
Version: 0.0.3
Summary: python package for relay device control
Home-page: https://bitbucket.org/opsys_tech/opsys-relay-controller/src/master/
Download-URL: https://bitbucket.org/opsys_tech/opsys-relay-controller/src/master/
Author: dmitry.borovensky
Author-email: dmitry.borovensky@opsys-tech.com
License-File: LICENSE
